nopip/__init__.py
nopip-0.2.2.dist-info/LICENSE
nopip-0.2.2.dist-info/METADATA
nopip-0.2.2.dist-info/WHEEL
nopip-0.2.2.dist-info/top_level.txt
nopip-0.2.2.dist-info/RECORD
