Metadata-Version: 2.1
Name: nopip
Version: 0.2.2
Summary: A simple module to install Python packages programmatically
Home-page: https://github.com/ronivaldo/nopip
Author: Ronivaldo Sampaio
Author-email: ronivaldo@gmail.com
Classifier: Development Status :: 3 - Alpha
Classifier: Intended Audience :: Developers
Classifier: License :: OSI Approved :: MIT License
Classifier: Programming Language :: Python
Classifier: Programming Language :: Python :: 3
Requires-Python: >=3.6
License-File: LICENSE
